CHANGES.txt
DEPENDENCES.txt
README.txt
setup.py
src/pd/__init__.py
src/pd.lib.egg-info/PKG-INFO
src/pd.lib.egg-info/SOURCES.txt
src/pd.lib.egg-info/dependency_links.txt
src/pd.lib.egg-info/namespace_packages.txt
src/pd.lib.egg-info/top_level.txt
src/pd.lib.egg-info/zip-safe
src/pd/lib/__init__.py
src/pd/lib/fuzzyobject.py
src/pd/lib/fuzzyobject_sample.py
src/pd/lib/gcd.py
src/pd/lib/heapsort.py
src/pd/lib/heapsort_new.py
src/pd/lib/hyphen.py
src/pd/lib/lazy.py
src/pd/lib/linear_quantizator.py
src/pd/lib/pd.lib.txt
src/pd/lib/topsort.py
src/pd/lib/utility.py