Metadata-Version: 1.0
Name: pd.lib
Version: 0.0.9
Summary: Library of small but useful modules
Home-page: http://www.dreambot.ru/dreambototherreleases/pd.lib
Author: Andrey Orlov
Author-email: dbdt@dreambot.ru
License: GPL v2.1
Platform: UNKNOWN
Classifier: Intended Audience :: Developers
Classifier: License :: OSI Approved :: GNU General Public License (GPL)
Classifier: Programming Language :: Python
Classifier: Operating System :: OS Independent
